gia/__init__.py
gia/aggregator.py
gia/cli.py
gia-1.0.0-py3.6.egg-info/PKG-INFO
gia-1.0.0-py3.6.egg-info/SOURCES.txt
gia-1.0.0-py3.6.egg-info/dependency_links.txt
gia-1.0.0-py3.6.egg-info/entry_points.txt
gia-1.0.0-py3.6.egg-info/requires.txt
gia-1.0.0-py3.6.egg-info/top_level.txt
gia-1.0.0.dist-info/dependency_links.txt
gia-1.0.0.dist-info/entry_points.txt
gia-1.0.0.dist-info/top_level.txt
gia-1.0.1.dist-info/DESCRIPTION.rst
gia-1.0.1.dist-info/METADATA
gia-1.0.1.dist-info/RECORD
gia-1.0.1.dist-info/WHEEL
gia-1.0.1.dist-info/entry_points.txt
gia-1.0.1.dist-info/metadata.json
gia-1.0.1.dist-info/top_level.txt
