Metadata-Version: 2.0
Name: gia
Version: 1.0.1
Summary: A powerful image aggregator for data science projects.
Home-page: https://github.com/cooperhammond/gia
Author: Cooper Hammond
Author-email: kepoorh@gmail.com
License: GPL
Platform: UNKNOWN
Requires-Dist: selenium
